mytrans/__init__.py
mytrans/deepl.py
mytrans/google.py
mytrans/run.py
mytrans-0.0.1.dist-info/LICENSE
mytrans-0.0.1.dist-info/METADATA
mytrans-0.0.1.dist-info/WHEEL
mytrans-0.0.1.dist-info/top_level.txt
mytrans-0.0.1.dist-info/RECORD
