Metadata-Version: 2.1
Name: mytrans
Version: 0.0.1
Summary: Free Translate(google/deepl) API for Python
Home-page: UNKNOWN
Author: Soul Drummer
Author-email: function@88.com
License: UNKNOWN
Platform: UNKNOWN
Classifier: Programming Language :: Python :: 2
Classifier: Programming Language :: Python :: 3
Classifier: License :: OSI Approved :: MIT License
Requires-Dist: requests
